torchmfbd/__init__.py
torchmfbd/az_average.py
torchmfbd/configuration.py
torchmfbd/convolvend.py
torchmfbd/deconvolution.py
torchmfbd/deconvolution_metapupil.py
torchmfbd/deconvolution_sv.py
torchmfbd/destretch.py
torchmfbd/diversity.py
torchmfbd/iuwt_torch.py
torchmfbd/kl_modes.py
torchmfbd/movie.py
torchmfbd/nmf.py
torchmfbd/noise.py
torchmfbd/noise_svd.py
torchmfbd/patchify4D.py
torchmfbd/patchify5D.py
torchmfbd/projection.py
torchmfbd/reg_iuwt.py
torchmfbd/reg_smooth.py
torchmfbd/regularization.py
torchmfbd/util.py
torchmfbd/warp.py
torchmfbd/zern.py
torchmfbd/kl/KL_variance
torchmfbd/kl/KL_variance_npy
torchmfbd/kl/check.py
torchmfbd/kl/kl_data_npy
torchmfbd/kl/zern.py
torchmfbd-0.9.2.dist-info/METADATA
torchmfbd-0.9.2.dist-info/WHEEL
torchmfbd-0.9.2.dist-info/licenses/LICENSE
torchmfbd-0.9.2.dist-info/RECORD
