Metadata-Version: 2.4
Name: torchmfbd
Version: 0.9.2
Summary: Multi-frame blind deconvolution with PyTorch
Author-email: "A. Asensio Ramos" <andres.asensio@iac.es>
License-File: LICENSE
Classifier: Development Status :: 4 - Beta
Classifier: Environment :: Console
Classifier: Intended Audience :: Developers
Classifier: Intended Audience :: Science/Research
Classifier: License :: OSI Approved :: GNU General Public License v3 (GPLv3)
Classifier: Operating System :: MacOS
Classifier: Operating System :: POSIX
Classifier: Operating System :: Unix
Classifier: Programming Language :: Python
Classifier: Programming Language :: Python :: 3.11
Classifier: Programming Language :: Python :: Implementation :: CPython
Classifier: Topic :: Scientific/Engineering
Classifier: Topic :: Scientific/Engineering :: Physics
Requires-Python: >=3.11.0
Requires-Dist: astropy>=7.0.1
Requires-Dist: dict-hash>=1.3.6
Requires-Dist: einops>=0.8.0
Requires-Dist: h5py>=3.13.0
Requires-Dist: matplotlib>=3.7.5
Requires-Dist: numpy>1.24.4
Requires-Dist: nvitop>=1.4.2
Requires-Dist: pyyaml>=6.0.2
Requires-Dist: scikit-image>=0.22.0
Requires-Dist: scikit-learn>=1.3.2
Requires-Dist: scipy>=1.10.1
Requires-Dist: torch>=2.6.0
Requires-Dist: tqdm>=4.67.1
